odoo10_addon_web_tree_many2one_clickable-10.0.1.0.0-py2.7-nspkg.pth
odoo10_addon_web_tree_many2one_clickable-10.0.1.0.0.dist-info/top_level.txt
odoo10_addon_web_tree_many2one_clickable-10.0.1.0.0.dist-info/WHEEL
odoo10_addon_web_tree_many2one_clickable-10.0.1.0.0.dist-info/RECORD
odoo10_addon_web_tree_many2one_clickable-10.0.1.0.0.dist-info/metadata.json
odoo10_addon_web_tree_many2one_clickable-10.0.1.0.0.dist-info/DESCRIPTION.rst
odoo10_addon_web_tree_many2one_clickable-10.0.1.0.0.dist-info/METADATA
odoo10_addon_web_tree_many2one_clickable-10.0.1.0.0.dist-info/namespace_packages.txt
odoo/addons/web_tree_many2one_clickable/__manifest__.py
odoo/addons/web_tree_many2one_clickable/__init__.py
odoo/addons/web_tree_many2one_clickable/README.rst
odoo/addons/web_tree_many2one_clickable/views/asset.xml
odoo/addons/web_tree_many2one_clickable/data/ir_config_parameter.xml
odoo/addons/web_tree_many2one_clickable/static/description/icon.png
odoo/addons/web_tree_many2one_clickable/static/src/js/web_tree_many2one_clickable.js
